dvd_rw/__init__.py
dvd_rw/loader.py
dvd_rw/models.py
dvd_rw/patcher.py
dvd_rw-0.1.6.dist-info/WHEEL
dvd_rw-0.1.6.dist-info/METADATA
dvd_rw-0.1.6.dist-info/RECORD
