Metadata-Version: 2.3
Name: dvd-rw
Version: 0.1.6
Summary: Speed-optimized request recording and replaying for HTTPX
Author: Lode Braced
Author-email: Lode Braced <lode@braced.dev>
Classifier: Development Status :: 4 - Beta
Classifier: License :: OSI Approved :: MIT License
Classifier: Intended Audience :: Developers
Classifier: Operating System :: OS Independent
Classifier: Programming Language :: Python
Classifier: Topic :: Software Development :: Libraries :: Python Modules
Classifier: Typing :: Typed
Requires-Dist: httpx>=0.28.1
Requires-Dist: pydantic>=2.11.7
Requires-Dist: uv-build>=0.8.5
Requires-Python: >=3.12
Project-URL: Repository, https://github.com/lode-braced/dvd-rw
